setup.py
python2sky/__init__.py
python2sky/bootstrap.py
python2sky/config.py
python2sky.egg-info/PKG-INFO
python2sky.egg-info/SOURCES.txt
python2sky.egg-info/dependency_links.txt
python2sky.egg-info/requires.txt
python2sky.egg-info/top_level.txt
python2sky/context/IgnoredTracerContext.py
python2sky/context/__init__.py
python2sky/context/common.py
python2sky/context/context_carrier.py
python2sky/context/context_manager.py
python2sky/context/noop_span.py
python2sky/context/span.py
python2sky/context/trace_context.py
python2sky/context/trace_segment.py
python2sky/exception/__init__.py
python2sky/exception/exceptions.py
python2sky/plugin/__init__.py
python2sky/plugin/flask_plugin.py
python2sky/plugin/requests_plugin.py
python2sky/plugin/trace_plugin.py
python2sky/plugin/urllib3_plugin.py
python2sky/plugin/urllib_plugin.py
python2sky/proto/__init__.py
python2sky/proto/common/CLR_pb2.py
python2sky/proto/common/CLR_pb2_grpc.py
python2sky/proto/common/JVM_pb2.py
python2sky/proto/common/JVM_pb2_grpc.py
python2sky/proto/common/__init__.py
python2sky/proto/common/common_pb2.py
python2sky/proto/common/common_pb2_grpc.py
python2sky/proto/common/trace_common_pb2.py
python2sky/proto/common/trace_common_pb2_grpc.py
python2sky/proto/language-agent/__init__.py
python2sky/proto/language_agent_v2/CLRMetric_pb2.py
python2sky/proto/language_agent_v2/CLRMetric_pb2_grpc.py
python2sky/proto/language_agent_v2/JVMMetric_pb2.py
python2sky/proto/language_agent_v2/JVMMetric_pb2_grpc.py
python2sky/proto/language_agent_v2/__init__.py
python2sky/proto/language_agent_v2/trace_pb2.py
python2sky/proto/language_agent_v2/trace_pb2_grpc.py
python2sky/proto/register/InstancePing_pb2.py
python2sky/proto/register/InstancePing_pb2_grpc.py
python2sky/proto/register/Register_pb2.py
python2sky/proto/register/Register_pb2_grpc.py
python2sky/proto/register/__init__.py
python2sky/proto/service-mesh-probe/__init__.py
python2sky/proto/service-mesh-probe/istio/__init__.py
python2sky/remote/__init__.py
python2sky/remote/service_register_client.py
python2sky/remote/trace_segment_client.py
python2sky/util/__init__.py
python2sky/util/base64_util.py
python2sky/util/common.py
